nfs_creator/__init__.py
nfs_creator/cmd_executor.py
nfs_creator/firewall_settings.py
nfs_creator/main.py
nfs_creator/nfs_installation_checker.py
nfs_creator/nfs_service.py
nfs_creator/open_permissions.py
nfs_creator/package_installer.py
nfs_creator-1.0.dist-info/METADATA
nfs_creator-1.0.dist-info/WHEEL
nfs_creator-1.0.dist-info/top_level.txt
nfs_creator-1.0.dist-info/RECORD
