Metadata-Version: 2.1
Name: nfs-creator
Version: 1.0
Summary: UNKNOWN
Home-page: UNKNOWN
License: UNKNOWN
Platform: UNKNOWN
Requires-Dist: distro (==1.9.0)
